{"dependencies":[{"name":"../core/snapshot_version","loc":{"line":18,"column":33}},{"name":"../model/collections","loc":{"line":19,"column":28}},{"name":"../model/document","loc":{"line":20,"column":25}},{"name":"../model/document_key","loc":{"line":21,"column":29}},{"name":"../util/assert","loc":{"line":22,"column":23}},{"name":"./persistence_promise","loc":{"line":23,"column":36}}],"generated":{"js":"\"use strict\";\n/**\n * Copyright 2017 Google Inc.\n *\n * Licensed under the Apache License, Version 2.0 (the \"License\");\n * you may not use this file except in compliance with the License.\n * You may obtain a copy of the License at\n *\n *   http://www.apache.org/licenses/LICENSE-2.0\n *\n * Unless required by applicable law or agreed to in writing, software\n * distributed under the License is distributed on an \"AS IS\" BASIS,\n * WITHOUT WARRANTIES OR CONDITIONS OF ANY KIND, either express or implied.\n * See the License for the specific language governing permissions and\n * limitations under the License.\n */\nObject.defineProperty(exports, \"__esModule\", { value: true });\nvar snapshot_version_1 = require(\"../core/snapshot_version\");\nvar collections_1 = require(\"../model/collections\");\nvar document_1 = require(\"../model/document\");\nvar document_key_1 = require(\"../model/document_key\");\nvar assert_1 = require(\"../util/assert\");\nvar persistence_promise_1 = require(\"./persistence_promise\");\n/**\n * A readonly view of the local state of all documents we're tracking (i.e. we\n * have a cached version in remoteDocumentCache or local mutations for the\n * document). The view is computed by applying the mutations in the\n * MutationQueue to the RemoteDocumentCache.\n */\nvar LocalDocumentsView = /** @class */ (function () {\n    function LocalDocumentsView(remoteDocumentCache, mutationQueue) {\n        this.remoteDocumentCache = remoteDocumentCache;\n        this.mutationQueue = mutationQueue;\n    }\n    /**\n     * Get the local view of the document identified by `key`.\n     *\n     * @return Local view of the document or null if we don't have any cached\n     * state for it.\n     */\n    LocalDocumentsView.prototype.getDocument = function (transaction, key) {\n        var _this = this;\n        return this.remoteDocumentCache\n            .getEntry(transaction, key)\n            .next(function (remoteDoc) {\n            return _this.computeLocalDocument(transaction, key, remoteDoc);\n        });\n    };\n    /**\n     * Gets the local view of the documents identified by `keys`.\n     *\n     * If we don't have cached state for a document in `keys`, a NoDocument will\n     * be stored for that key in the resulting set.\n     */\n    LocalDocumentsView.prototype.getDocuments = function (transaction, keys) {\n        var _this = this;\n        var promises = [];\n        var results = collections_1.maybeDocumentMap();\n        keys.forEach(function (key) {\n            promises.push(_this.getDocument(transaction, key).next(function (maybeDoc) {\n                // TODO(http://b/32275378): Don't conflate missing / deleted.\n                if (!maybeDoc) {\n                    maybeDoc = new document_1.NoDocument(key, snapshot_version_1.SnapshotVersion.forDeletedDoc());\n                }\n                results = results.insert(key, maybeDoc);\n            }));\n        });\n        return persistence_promise_1.PersistencePromise.waitFor(promises).next(function () { return results; });\n    };\n    /** Performs a query against the local view of all documents. */\n    LocalDocumentsView.prototype.getDocumentsMatchingQuery = function (transaction, query) {\n        if (document_key_1.DocumentKey.isDocumentKey(query.path)) {\n            return this.getDocumentsMatchingDocumentQuery(transaction, query.path);\n        }\n        else {\n            return this.getDocumentsMatchingCollectionQuery(transaction, query);\n        }\n    };\n    LocalDocumentsView.prototype.getDocumentsMatchingDocumentQuery = function (transaction, docPath) {\n        // Just do a simple document lookup.\n        return this.getDocument(transaction, new document_key_1.DocumentKey(docPath)).next(function (maybeDoc) {\n            var result = collections_1.documentMap();\n            if (maybeDoc instanceof document_1.Document) {\n                result = result.insert(maybeDoc.key, maybeDoc);\n            }\n            return result;\n        });\n    };\n    LocalDocumentsView.prototype.getDocumentsMatchingCollectionQuery = function (transaction, query) {\n        var _this = this;\n        // Query the remote documents and overlay mutations.\n        // TODO(mikelehen): There may be significant overlap between the mutations\n        // affecting these remote documents and the\n        // getAllMutationBatchesAffectingQuery() mutations. Consider optimizing.\n        var results;\n        return this.remoteDocumentCache\n            .getDocumentsMatchingQuery(transaction, query)\n            .next(function (queryResults) {\n            return _this.computeLocalDocuments(transaction, queryResults);\n        })\n            .next(function (promisedResults) {\n            results = promisedResults;\n            // Now use the mutation queue to discover any other documents that may\n            // match the query after applying mutations.\n            return _this.mutationQueue.getAllMutationBatchesAffectingQuery(transaction, query);\n        })\n            .next(function (matchingMutationBatches) {\n            var matchingKeys = collections_1.documentKeySet();\n            for (var _i = 0, matchingMutationBatches_1 = matchingMutationBatches; _i < matchingMutationBatches_1.length; _i++) {\n                var batch = matchingMutationBatches_1[_i];\n                for (var _a = 0, _b = batch.mutations; _a < _b.length; _a++) {\n                    var mutation = _b[_a];\n                    // TODO(mikelehen): PERF: Check if this mutation actually\n                    // affects the query to reduce work.\n                    if (!results.get(mutation.key)) {\n                        matchingKeys = matchingKeys.add(mutation.key);\n                    }\n                }\n            }\n            // Now add in the results for the matchingKeys.\n            var promises = [];\n            matchingKeys.forEach(function (key) {\n                promises.push(_this.getDocument(transaction, key).next(function (doc) {\n                    if (doc instanceof document_1.Document) {\n                        results = results.insert(doc.key, doc);\n                    }\n                }));\n            });\n            return persistence_promise_1.PersistencePromise.waitFor(promises);\n        })\n            .next(function () {\n            // Finally, filter out any documents that don't actually match\n            // the query.\n            results.forEach(function (key, doc) {\n                if (!query.matches(doc)) {\n                    results = results.remove(key);\n                }\n            });\n            return results;\n        });\n    };\n    /**\n     * Takes a remote document and applies local mutations to generate the local\n     * view of the document.\n     * @param transaction The transaction in which to perform any persistence\n     *     operations.\n     * @param documentKey The key of the document (necessary when remoteDocument\n     *     is null).\n     * @param document The base remote document to apply mutations to or null.\n     */\n    LocalDocumentsView.prototype.computeLocalDocument = function (transaction, documentKey, document) {\n        return this.mutationQueue\n            .getAllMutationBatchesAffectingDocumentKey(transaction, documentKey)\n            .next(function (batches) {\n            for (var _i = 0, batches_1 = batches; _i < batches_1.length; _i++) {\n                var batch = batches_1[_i];\n                document = batch.applyToLocalView(documentKey, document);\n            }\n            return document;\n        });\n    };\n    /**\n     * Takes a set of remote documents and applies local mutations to generate the\n     * local view of the documents.\n     * @param transaction The transaction in which to perform any persistence\n     *     operations.\n     * @param documents The base remote documents to apply mutations to.\n     * @return The local view of the documents.\n     */\n    LocalDocumentsView.prototype.computeLocalDocuments = function (transaction, documents) {\n        var _this = this;\n        var promises = [];\n        documents.forEach(function (key, doc) {\n            promises.push(_this.computeLocalDocument(transaction, key, doc).next(function (mutatedDoc) {\n                if (mutatedDoc instanceof document_1.Document) {\n                    documents = documents.insert(mutatedDoc.key, mutatedDoc);\n                }\n                else if (mutatedDoc instanceof document_1.NoDocument) {\n                    documents = documents.remove(mutatedDoc.key);\n                }\n                else {\n                    assert_1.fail('Unknown MaybeDocument: ' + mutatedDoc);\n                }\n            }));\n        });\n        return persistence_promise_1.PersistencePromise.waitFor(promises).next(function () { return documents; });\n    };\n    return LocalDocumentsView;\n}());\nexports.LocalDocumentsView = LocalDocumentsView;\n\n//# sourceMappingURL=local_documents_view.js.map\n"},"hash":"e4e594f2ca7b5aa13fd499ca4c211f45"}